{
  "permalink": "/blog/2020/10/24/bootcamp4",
  "source": "@site/blog/2020-10-24-bootcamp4.md",
  "title": "Building a lyrics scraper and classifier in Python",
  "description": "Project completed in week 4 (19.10.-23.10.20) of the Data Science Bootcamp at Spiced Academy in Berlin.",
  "date": "2020-10-24T00:00:00.000Z",
  "formattedDate": "October 24, 2020",
  "tags": [
    {
      "label": "data science",
      "permalink": "/blog/tags/data-science"
    },
    {
      "label": "bootcamp",
      "permalink": "/blog/tags/bootcamp"
    },
    {
      "label": "tutorials",
      "permalink": "/blog/tags/tutorials"
    },
    {
      "label": "Python",
      "permalink": "/blog/tags/python"
    },
    {
      "label": "NLP",
      "permalink": "/blog/tags/nlp"
    }
  ],
  "readingTime": 3.13,
  "truncated": false,
  "authors": [],
  "frontMatter": {
    "layout": "post",
    "title": "Building a lyrics scraper and classifier in Python",
    "gh-repo": "lorenanda/lyrics-classification",
    "gh-badge": [
      "star",
      "fork",
      "follow"
    ],
    "tags": [
      "data science",
      "bootcamp",
      "tutorials",
      "Python",
      "NLP"
    ],
    "comments": true
  },
  "prevItem": {
    "title": "Forecasting the weather in Berlin with ARIMA models",
    "permalink": "/blog/2020/10/31/bootcamp5"
  },
  "nextItem": {
    "title": "Predicting bike share demand with linear regression",
    "permalink": "/blog/2020/10/17/bootcamp3"
  }
}